async_sdnotify/__init__.py
async_sdnotify/py.typed
async_sdnotify-0.1.0.post2.dist-info/LICENSE.txt
async_sdnotify-0.1.0.post2.dist-info/METADATA
async_sdnotify-0.1.0.post2.dist-info/WHEEL
async_sdnotify-0.1.0.post2.dist-info/RECORD
