Metadata-Version: 2.3
Name: async-sdnotify
Version: 0.1.0.post2
Summary: A pure asynchronous Python implementation of systemd's service notification protocol (sd_notify)
License: MIT
Author: Calian Ltd.
Author-email: zach.mayoh@calian.com
Requires-Python: >=3.12
Classifier: Intended Audience :: Developers
Classifier: Operating System :: POSIX :: Linux
Classifier: Topic :: Software Development :: Libraries :: Python Modules
